[
    {
        "code": "3276071004",
        "name": "Bojong Pondok Terong",
        "poscode": "16436"
    },
    {
        "code": "3276071001",
        "name": "Cipayung",
        "poscode": "16437"
    },
    {
        "code": "3276071002",
        "name": "Cipayung Jaya",
        "poscode": "16437"
    },
    {
        "code": "3276071005",
        "name": "Pondok Jaya (Pondokjaya)",
        "poscode": "16438"
    },
    {
        "code": "3276071003",
        "name": "Ratu Jaya",
        "poscode": "16439"
    }
]