[
    {
        "code": "1214292007",
        "name": "Bawolawindra",
        "poscode": "22883"
    },
    {
        "code": "1214292004",
        "name": "Bawositora",
        "poscode": "22883"
    },
    {
        "code": "1214292005",
        "name": "Bintuang",
        "poscode": "22883"
    },
    {
        "code": "1214292001",
        "name": "Fuge",
        "poscode": "22883"
    },
    {
        "code": "1214292008",
        "name": "Hayo",
        "poscode": "22883"
    },
    {
        "code": "1214292009",
        "name": "Hilizamorogotano",
        "poscode": "22883"
    },
    {
        "code": "1214292002",
        "name": "Luaha Idano Pono (Luaha Idanopono)",
        "poscode": "22883"
    },
    {
        "code": "1214292006",
        "name": "Sibaranun",
        "poscode": "22883"
    },
    {
        "code": "1214292003",
        "name": "Sigese",
        "poscode": "22883"
    }
]