[
    {
        "no": "1",
        "kodepos": "27373",
        "name": "Lolo",
        "detail_link": "https://kodepos.nomor.net/_kodepos.php?_i=desa-kodepos&sby=000000&daerah=Desa-Pantai%20Cermin-Kab.-Solok&jobs=Lolo",
        "kode": "13.02.03.2001"
    },
    {
        "no": "2",
        "kodepos": "27373",
        "name": "Surian",
        "detail_link": "https://kodepos.nomor.net/_kodepos.php?_i=desa-kodepos&sby=000000&daerah=Desa-Pantai%20Cermin-Kab.-Solok&jobs=Surian",
        "kode": "13.02.03.2002"
    }
]