[
    {
        "no": "1",
        "kodepos": "91984",
        "name": "Lamunre",
        "detail_link": "https://kodepos.nomor.net/_kodepos.php?_i=desa-kodepos&sby=000000&daerah=Desa-Belopa%20Utara-Kab.-Luwu&jobs=Lamunre",
        "kode": "73.17.14.2002"
    },
    {
        "no": "2",
        "kodepos": "91984",
        "name": "Lamunre Tengah",
        "detail_link": "https://kodepos.nomor.net/_kodepos.php?_i=desa-kodepos&sby=000000&daerah=Desa-Belopa%20Utara-Kab.-Luwu&jobs=Lamunre%20Tengah",
        "kode": "73.17.14.2008"
    },
    {
        "no": "3",
        "kodepos": "91984",
        "name": "Lauwa",
        "detail_link": "https://kodepos.nomor.net/_kodepos.php?_i=desa-kodepos&sby=000000&daerah=Desa-Belopa%20Utara-Kab.-Luwu&jobs=Lauwa",
        "kode": "73.17.14.2003"
    },
    {
        "no": "4",
        "kodepos": "91984",
        "name": "Lebani",
        "detail_link": "https://kodepos.nomor.net/_kodepos.php?_i=desa-kodepos&sby=000000&daerah=Desa-Belopa%20Utara-Kab.-Luwu&jobs=Lebani",
        "kode": "73.17.14.2007"
    },
    {
        "no": "5",
        "kodepos": "91984",
        "name": "Paconne",
        "detail_link": "https://kodepos.nomor.net/_kodepos.php?_i=desa-kodepos&sby=000000&daerah=Desa-Belopa%20Utara-Kab.-Luwu&jobs=Paconne",
        "kode": "73.17.14.2006"
    },
    {
        "no": "6",
        "kodepos": "91984",
        "name": "Pammanu",
        "detail_link": "https://kodepos.nomor.net/_kodepos.php?_i=desa-kodepos&sby=000000&daerah=Desa-Belopa%20Utara-Kab.-Luwu&jobs=Pammanu",
        "kode": "73.17.14.1004"
    },
    {
        "no": "7",
        "kodepos": "91984",
        "name": "Sabe",
        "detail_link": "https://kodepos.nomor.net/_kodepos.php?_i=desa-kodepos&sby=000000&daerah=Desa-Belopa%20Utara-Kab.-Luwu&jobs=Sabe",
        "kode": "73.17.14.1001"
    },
    {
        "no": "8",
        "kodepos": "91984",
        "name": "Seppong",
        "detail_link": "https://kodepos.nomor.net/_kodepos.php?_i=desa-kodepos&sby=000000&daerah=Desa-Belopa%20Utara-Kab.-Luwu&jobs=Seppong",
        "kode": "73.17.14.2005"
    }
]