[
    {
        "no": "1",
        "kodepos": "24791",
        "name": "Pulau Baguk",
        "detail_link": "https://kodepos.nomor.net/_kodepos.php?_i=desa-kodepos&sby=000000&daerah=Desa-Pulau%20Banyak-Kab.-Aceh%20Singkil&jobs=Pulau%20Baguk",
        "kode": "11.10.01.2002"
    },
    {
        "no": "2",
        "kodepos": "24791",
        "name": "Pulau Balai",
        "detail_link": "https://kodepos.nomor.net/_kodepos.php?_i=desa-kodepos&sby=000000&daerah=Desa-Pulau%20Banyak-Kab.-Aceh%20Singkil&jobs=Pulau%20Balai",
        "kode": "11.10.01.2001"
    },
    {
        "no": "3",
        "kodepos": "24791",
        "name": "Teluk Nibung",
        "detail_link": "https://kodepos.nomor.net/_kodepos.php?_i=desa-kodepos&sby=000000&daerah=Desa-Pulau%20Banyak-Kab.-Aceh%20Singkil&jobs=Teluk%20Nibung",
        "kode": "11.10.01.2004"
    }
]