[
    {
        "no": "1",
        "kodepos": "95715",
        "name": "Gogagoman",
        "detail_link": "https://kodepos.nomor.net/_kodepos.php?_i=desa-kodepos&sby=000000&daerah=Desa-Kotamobagu%20Barat-Kota-Kotamobagu&jobs=Gogagoman",
        "kode": "71.74.04.1004"
    },
    {
        "no": "2",
        "kodepos": "95711",
        "name": "Kotamobagu",
        "detail_link": "https://kodepos.nomor.net/_kodepos.php?_i=desa-kodepos&sby=000000&daerah=Desa-Kotamobagu%20Barat-Kota-Kotamobagu&jobs=Kotamobagu",
        "kode": "71.74.04.1005"
    },
    {
        "no": "3",
        "kodepos": "95716",
        "name": "Mogolaing",
        "detail_link": "https://kodepos.nomor.net/_kodepos.php?_i=desa-kodepos&sby=000000&daerah=Desa-Kotamobagu%20Barat-Kota-Kotamobagu&jobs=Mogolaing",
        "kode": "71.74.04.1003"
    },
    {
        "no": "4",
        "kodepos": "95716",
        "name": "Molinow",
        "detail_link": "https://kodepos.nomor.net/_kodepos.php?_i=desa-kodepos&sby=000000&daerah=Desa-Kotamobagu%20Barat-Kota-Kotamobagu&jobs=Molinow",
        "kode": "71.74.04.1002"
    },
    {
        "no": "5",
        "kodepos": "95716",
        "name": "Mongkonai",
        "detail_link": "https://kodepos.nomor.net/_kodepos.php?_i=desa-kodepos&sby=000000&daerah=Desa-Kotamobagu%20Barat-Kota-Kotamobagu&jobs=Mongkonai",
        "kode": "71.74.04.1001"
    },
    {
        "no": "6",
        "kodepos": "95716",
        "name": "Mongkonai Barat",
        "detail_link": "https://kodepos.nomor.net/_kodepos.php?_i=desa-kodepos&sby=000000&daerah=Desa-Kotamobagu%20Barat-Kota-Kotamobagu&jobs=Mongkonai%20Barat",
        "kode": "71.74.04.1006"
    }
]