[
    {
        "no": "1",
        "kodepos": "68424",
        "name": "Boyolangu",
        "detail_link": "https://kodepos.nomor.net/_kodepos.php?_i=desa-kodepos&sby=000000&daerah=Desa-Giri-Kab.-Banyuwangi&jobs=Boyolangu",
        "kode": "35.10.17.1002"
    },
    {
        "no": "2",
        "kodepos": "68423",
        "name": "Giri",
        "detail_link": "https://kodepos.nomor.net/_kodepos.php?_i=desa-kodepos&sby=000000&daerah=Desa-Giri-Kab.-Banyuwangi&jobs=Giri",
        "kode": "35.10.17.1005"
    },
    {
        "no": "3",
        "kodepos": "68425",
        "name": "Grogol",
        "detail_link": "https://kodepos.nomor.net/_kodepos.php?_i=desa-kodepos&sby=000000&daerah=Desa-Giri-Kab.-Banyuwangi&jobs=Grogol",
        "kode": "35.10.17.2006"
    },
    {
        "no": "4",
        "kodepos": "68425",
        "name": "Jambesari",
        "detail_link": "https://kodepos.nomor.net/_kodepos.php?_i=desa-kodepos&sby=000000&daerah=Desa-Giri-Kab.-Banyuwangi&jobs=Jambesari",
        "kode": "35.10.17.2001"
    },
    {
        "no": "5",
        "kodepos": "68425",
        "name": "Mojopanggung",
        "detail_link": "https://kodepos.nomor.net/_kodepos.php?_i=desa-kodepos&sby=000000&daerah=Desa-Giri-Kab.-Banyuwangi&jobs=Mojopanggung",
        "kode": "35.10.17.1003"
    },
    {
        "no": "6",
        "kodepos": "68422",
        "name": "Penataban",
        "detail_link": "https://kodepos.nomor.net/_kodepos.php?_i=desa-kodepos&sby=000000&daerah=Desa-Giri-Kab.-Banyuwangi&jobs=Penataban",
        "kode": "35.10.17.1004"
    }
]