[
    {
        "no": "1",
        "kodepos": "30257",
        "name": "15 Ulu",
        "detail_link": "https://kodepos.nomor.net/_kodepos.php?_i=desa-kodepos&sby=000000&daerah=Desa-Jakabaring-Kota-Palembang&jobs=15%20Ulu",
        "kode": "16.71.17.1003"
    },
    {
        "no": "2",
        "kodepos": "30252",
        "name": "8 Ulu",
        "detail_link": "https://kodepos.nomor.net/_kodepos.php?_i=desa-kodepos&sby=000000&daerah=Desa-Jakabaring-Kota-Palembang&jobs=8%20Ulu",
        "kode": "16.71.17.1001"
    },
    {
        "no": "3",
        "kodepos": "30251",
        "name": "9-10 Ulu",
        "detail_link": "https://kodepos.nomor.net/_kodepos.php?_i=desa-kodepos&sby=000000&daerah=Desa-Jakabaring-Kota-Palembang&jobs=9-10%20Ulu",
        "kode": "16.71.17.1002"
    },
    {
        "no": "4",
        "kodepos": "30251",
        "name": "Silaberanti",
        "detail_link": "https://kodepos.nomor.net/_kodepos.php?_i=desa-kodepos&sby=000000&daerah=Desa-Jakabaring-Kota-Palembang&jobs=Silaberanti",
        "kode": "16.71.17.1004"
    },
    {
        "no": "5",
        "kodepos": "30251",
        "name": "Tuan Kentang",
        "detail_link": "https://kodepos.nomor.net/_kodepos.php?_i=desa-kodepos&sby=000000&daerah=Desa-Jakabaring-Kota-Palembang&jobs=Tuan%20Kentang",
        "kode": "16.71.17.1005"
    }
]