[
    {
        "no": "1",
        "kodepos": "66284",
        "name": "Demuk",
        "detail_link": "https://kodepos.nomor.net/_kodepos.php?_i=desa-kodepos&sby=000000&daerah=Desa-Pucanglaban-Kab.-Tulungagung&jobs=Demuk",
        "kode": "35.04.12.2009"
    },
    {
        "no": "2",
        "kodepos": "66284",
        "name": "Kalidawe",
        "detail_link": "https://kodepos.nomor.net/_kodepos.php?_i=desa-kodepos&sby=000000&daerah=Desa-Pucanglaban-Kab.-Tulungagung&jobs=Kalidawe",
        "kode": "35.04.12.2002"
    },
    {
        "no": "3",
        "kodepos": "66284",
        "name": "Kaligentong",
        "detail_link": "https://kodepos.nomor.net/_kodepos.php?_i=desa-kodepos&sby=000000&daerah=Desa-Pucanglaban-Kab.-Tulungagung&jobs=Kaligentong",
        "kode": "35.04.12.2004"
    },
    {
        "no": "4",
        "kodepos": "66284",
        "name": "Manding",
        "detail_link": "https://kodepos.nomor.net/_kodepos.php?_i=desa-kodepos&sby=000000&daerah=Desa-Pucanglaban-Kab.-Tulungagung&jobs=Manding",
        "kode": "35.04.12.2006"
    },
    {
        "no": "5",
        "kodepos": "66284",
        "name": "Panggungkalak",
        "detail_link": "https://kodepos.nomor.net/_kodepos.php?_i=desa-kodepos&sby=000000&daerah=Desa-Pucanglaban-Kab.-Tulungagung&jobs=Panggungkalak",
        "kode": "35.04.12.2003"
    },
    {
        "no": "6",
        "kodepos": "66284",
        "name": "Panggunguni",
        "detail_link": "https://kodepos.nomor.net/_kodepos.php?_i=desa-kodepos&sby=000000&daerah=Desa-Pucanglaban-Kab.-Tulungagung&jobs=Panggunguni",
        "kode": "35.04.12.2007"
    },
    {
        "no": "7",
        "kodepos": "66284",
        "name": "Pucanglaban",
        "detail_link": "https://kodepos.nomor.net/_kodepos.php?_i=desa-kodepos&sby=000000&daerah=Desa-Pucanglaban-Kab.-Tulungagung&jobs=Pucanglaban",
        "kode": "35.04.12.2001"
    },
    {
        "no": "8",
        "kodepos": "66284",
        "name": "Sumberbendo",
        "detail_link": "https://kodepos.nomor.net/_kodepos.php?_i=desa-kodepos&sby=000000&daerah=Desa-Pucanglaban-Kab.-Tulungagung&jobs=Sumberbendo",
        "kode": "35.04.12.2005"
    },
    {
        "no": "9",
        "kodepos": "66284",
        "name": "Sumberdadap",
        "detail_link": "https://kodepos.nomor.net/_kodepos.php?_i=desa-kodepos&sby=000000&daerah=Desa-Pucanglaban-Kab.-Tulungagung&jobs=Sumberdadap",
        "kode": "35.04.12.2008"
    }
]