[
    {
        "no": "1",
        "kodepos": "84181",
        "name": "Ka'owa",
        "detail_link": "https://kodepos.nomor.net/_kodepos.php?_i=desa-kodepos&sby=000000&daerah=Desa-Lambitu-Kab.-Bima&jobs=Ka%27owa",
        "kode": "52.06.17.2005"
    },
    {
        "no": "2",
        "kodepos": "84181",
        "name": "Kabaro",
        "detail_link": "https://kodepos.nomor.net/_kodepos.php?_i=desa-kodepos&sby=000000&daerah=Desa-Lambitu-Kab.-Bima&jobs=Kabaro",
        "kode": "52.06.17.2001"
    },
    {
        "no": "3",
        "kodepos": "84181",
        "name": "Kuta",
        "detail_link": "https://kodepos.nomor.net/_kodepos.php?_i=desa-kodepos&sby=000000&daerah=Desa-Lambitu-Kab.-Bima&jobs=Kuta",
        "kode": "52.06.17.2002"
    },
    {
        "no": "4",
        "kodepos": "84181",
        "name": "Londu",
        "detail_link": "https://kodepos.nomor.net/_kodepos.php?_i=desa-kodepos&sby=000000&daerah=Desa-Lambitu-Kab.-Bima&jobs=Londu",
        "kode": "52.06.17.2006"
    },
    {
        "no": "5",
        "kodepos": "84181",
        "name": "Sambori",
        "detail_link": "https://kodepos.nomor.net/_kodepos.php?_i=desa-kodepos&sby=000000&daerah=Desa-Lambitu-Kab.-Bima&jobs=Sambori",
        "kode": "52.06.17.2003"
    },
    {
        "no": "6",
        "kodepos": "84181",
        "name": "Teta",
        "detail_link": "https://kodepos.nomor.net/_kodepos.php?_i=desa-kodepos&sby=000000&daerah=Desa-Lambitu-Kab.-Bima&jobs=Teta",
        "kode": "52.06.17.2004"
    }
]