[
    {
        "code": "3604152006",
        "name": "Bakung",
        "poscode": "42186"
    },
    {
        "code": "3604152001",
        "name": "Cikande",
        "poscode": "42186"
    },
    {
        "code": "3604152013",
        "name": "Cikande Permai",
        "poscode": "42186"
    },
    {
        "code": "3604152011",
        "name": "Gembor Udik",
        "poscode": "42186"
    },
    {
        "code": "3604152007",
        "name": "Julang",
        "poscode": "42186"
    },
    {
        "code": "3604152010",
        "name": "Kamurang",
        "poscode": "42186"
    },
    {
        "code": "3604152005",
        "name": "Koper",
        "poscode": "42186"
    },
    {
        "code": "3604152002",
        "name": "Leuwi Limus (Leuwilimus)",
        "poscode": "42186"
    },
    {
        "code": "3604152003",
        "name": "Nambo Udik",
        "poscode": "42186"
    },
    {
        "code": "3604152004",
        "name": "Parigi",
        "poscode": "42186"
    },
    {
        "code": "3604152009",
        "name": "Situterate",
        "poscode": "42186"
    },
    {
        "code": "3604152012",
        "name": "Songgomjaya (Songgom Jaya)",
        "poscode": "42186"
    },
    {
        "code": "3604152008",
        "name": "Sukatani",
        "poscode": "42186"
    }
]