[
    {
        "no": "1",
        "name": "Adian Koting",
        "detail_link": "https://kodepos.nomor.net/_kodepos.php?_i=desa-kodepos&sby=000000&daerah=Kecamatan-Kab.-Tapanuli%20Utara&jobs=Adian%20Koting",
        "kodepos": [
            "22461"
        ],
        "desa": {
            "href": "https://kodepos.nomor.net/_kodepos.php?_i=desa-kodepos&sby=000000&daerah=Kecamatan-Kab.-Tapanuli%20Utara&jobs=Adian%20Koting",
            "jumlah": "16"
        },
        "pulau": null,
        "kode": "12.02.03"
    },
    {
        "no": "2",
        "name": "Garoga",
        "detail_link": "https://kodepos.nomor.net/_kodepos.php?_i=desa-kodepos&sby=000000&daerah=Kecamatan-Kab.-Tapanuli%20Utara&jobs=Garoga",
        "kodepos": [
            "22473"
        ],
        "desa": {
            "href": "https://kodepos.nomor.net/_kodepos.php?_i=desa-kodepos&sby=000000&daerah=Kecamatan-Kab.-Tapanuli%20Utara&jobs=Garoga",
            "jumlah": "13"
        },
        "pulau": null,
        "kode": "12.02.14"
    },
    {
        "no": "3",
        "name": "Muara",
        "detail_link": "https://kodepos.nomor.net/_kodepos.php?_i=desa-kodepos&sby=000000&daerah=Kecamatan-Kab.-Tapanuli%20Utara&jobs=Muara",
        "kodepos": [
            "22476"
        ],
        "desa": {
            "href": "https://kodepos.nomor.net/_kodepos.php?_i=desa-kodepos&sby=000000&daerah=Kecamatan-Kab.-Tapanuli%20Utara&jobs=Muara",
            "jumlah": "15"
        },
        "pulau": {
            "href": "https://kodepos.nomor.net/_kodepos.php?_i=pulau-kodepos&sby=000000&daerah=Kecamatan-Kab.-Tapanuli%20Utara&jobs=Muara",
            "jumlah": "1"
        },
        "kode": "12.02.15"
    },
    {
        "no": "4",
        "name": "Pagaran",
        "detail_link": "https://kodepos.nomor.net/_kodepos.php?_i=desa-kodepos&sby=000000&daerah=Kecamatan-Kab.-Tapanuli%20Utara&jobs=Pagaran",
        "kodepos": [
            "22458"
        ],
        "desa": {
            "href": "https://kodepos.nomor.net/_kodepos.php?_i=desa-kodepos&sby=000000&daerah=Kecamatan-Kab.-Tapanuli%20Utara&jobs=Pagaran",
            "jumlah": "14"
        },
        "pulau": null,
        "kode": "12.02.10"
    },
    {
        "no": "5",
        "name": "Pahae Jae",
        "detail_link": "https://kodepos.nomor.net/_kodepos.php?_i=desa-kodepos&sby=000000&daerah=Kecamatan-Kab.-Tapanuli%20Utara&jobs=Pahae%20Jae",
        "kodepos": [
            "22465"
        ],
        "desa": {
            "href": "https://kodepos.nomor.net/_kodepos.php?_i=desa-kodepos&sby=000000&daerah=Kecamatan-Kab.-Tapanuli%20Utara&jobs=Pahae%20Jae",
            "jumlah": "13"
        },
        "pulau": null,
        "kode": "12.02.06"
    },
    {
        "no": "6",
        "name": "Pahae Julu",
        "detail_link": "https://kodepos.nomor.net/_kodepos.php?_i=desa-kodepos&sby=000000&daerah=Kecamatan-Kab.-Tapanuli%20Utara&jobs=Pahae%20Julu",
        "kodepos": [
            "22463"
        ],
        "desa": {
            "href": "https://kodepos.nomor.net/_kodepos.php?_i=desa-kodepos&sby=000000&daerah=Kecamatan-Kab.-Tapanuli%20Utara&jobs=Pahae%20Julu",
            "jumlah": "19"
        },
        "pulau": null,
        "kode": "12.02.05"
    },
    {
        "no": "7",
        "name": "Pangaribuan",
        "detail_link": "https://kodepos.nomor.net/_kodepos.php?_i=desa-kodepos&sby=000000&daerah=Kecamatan-Kab.-Tapanuli%20Utara&jobs=Pangaribuan",
        "kodepos": [
            "22472"
        ],
        "desa": {
            "href": "https://kodepos.nomor.net/_kodepos.php?_i=desa-kodepos&sby=000000&daerah=Kecamatan-Kab.-Tapanuli%20Utara&jobs=Pangaribuan",
            "jumlah": "26"
        },
        "pulau": null,
        "kode": "12.02.13"
    },
    {
        "no": "8",
        "name": "Parmonangan",
        "detail_link": "https://kodepos.nomor.net/_kodepos.php?_i=desa-kodepos&sby=000000&daerah=Kecamatan-Kab.-Tapanuli%20Utara&jobs=Parmonangan",
        "kodepos": [
            "22453"
        ],
        "desa": {
            "href": "https://kodepos.nomor.net/_kodepos.php?_i=desa-kodepos&sby=000000&daerah=Kecamatan-Kab.-Tapanuli%20Utara&jobs=Parmonangan",
            "jumlah": "14"
        },
        "pulau": null,
        "kode": "12.02.11"
    },
    {
        "no": "9",
        "name": "Purba Tua (Purbatua)",
        "detail_link": "https://kodepos.nomor.net/_kodepos.php?_i=desa-kodepos&sby=000000&daerah=Kecamatan-Kab.-Tapanuli%20Utara&jobs=Purba%20Tua%20(Purbatua)",
        "kodepos": [
            "22464"
        ],
        "desa": {
            "href": "https://kodepos.nomor.net/_kodepos.php?_i=desa-kodepos&sby=000000&daerah=Kecamatan-Kab.-Tapanuli%20Utara&jobs=Purba%20Tua%20(Purbatua)",
            "jumlah": "11"
        },
        "pulau": null,
        "kode": "12.02.08"
    },
    {
        "no": "10",
        "name": "Siatas Barita",
        "detail_link": "https://kodepos.nomor.net/_kodepos.php?_i=desa-kodepos&sby=000000&daerah=Kecamatan-Kab.-Tapanuli%20Utara&jobs=Siatas%20Barita",
        "kodepos": [
            "22417",
            "22419"
        ],
        "desa": {
            "href": "https://kodepos.nomor.net/_kodepos.php?_i=desa-kodepos&sby=000000&daerah=Kecamatan-Kab.-Tapanuli%20Utara&jobs=Siatas%20Barita",
            "jumlah": "12"
        },
        "pulau": null,
        "kode": "12.02.02"
    },
    {
        "no": "11",
        "name": "Siborong-Borong",
        "detail_link": "https://kodepos.nomor.net/_kodepos.php?_i=desa-kodepos&sby=000000&daerah=Kecamatan-Kab.-Tapanuli%20Utara&jobs=Siborong-Borong",
        "kodepos": [
            "22474"
        ],
        "desa": {
            "href": "https://kodepos.nomor.net/_kodepos.php?_i=desa-kodepos&sby=000000&daerah=Kecamatan-Kab.-Tapanuli%20Utara&jobs=Siborong-Borong",
            "jumlah": "21"
        },
        "pulau": null,
        "kode": "12.02.09"
    },
    {
        "no": "12",
        "name": "Simangumban",
        "detail_link": "https://kodepos.nomor.net/_kodepos.php?_i=desa-kodepos&sby=000000&daerah=Kecamatan-Kab.-Tapanuli%20Utara&jobs=Simangumban",
        "kodepos": [
            "22466"
        ],
        "desa": {
            "href": "https://kodepos.nomor.net/_kodepos.php?_i=desa-kodepos&sby=000000&daerah=Kecamatan-Kab.-Tapanuli%20Utara&jobs=Simangumban",
            "jumlah": "8"
        },
        "pulau": null,
        "kode": "12.02.07"
    },
    {
        "no": "13",
        "name": "Sipahutar",
        "detail_link": "https://kodepos.nomor.net/_kodepos.php?_i=desa-kodepos&sby=000000&daerah=Kecamatan-Kab.-Tapanuli%20Utara&jobs=Sipahutar",
        "kodepos": [
            "22471"
        ],
        "desa": {
            "href": "https://kodepos.nomor.net/_kodepos.php?_i=desa-kodepos&sby=000000&daerah=Kecamatan-Kab.-Tapanuli%20Utara&jobs=Sipahutar",
            "jumlah": "25"
        },
        "pulau": null,
        "kode": "12.02.12"
    },
    {
        "no": "14",
        "name": "Sipoholon",
        "detail_link": "https://kodepos.nomor.net/_kodepos.php?_i=desa-kodepos&sby=000000&daerah=Kecamatan-Kab.-Tapanuli%20Utara&jobs=Sipoholon",
        "kodepos": [
            "22452"
        ],
        "desa": {
            "href": "https://kodepos.nomor.net/_kodepos.php?_i=desa-kodepos&sby=000000&daerah=Kecamatan-Kab.-Tapanuli%20Utara&jobs=Sipoholon",
            "jumlah": "14"
        },
        "pulau": null,
        "kode": "12.02.04"
    },
    {
        "no": "15",
        "name": "Tarutung",
        "detail_link": "https://kodepos.nomor.net/_kodepos.php?_i=desa-kodepos&sby=000000&daerah=Kecamatan-Kab.-Tapanuli%20Utara&jobs=Tarutung",
        "kodepos": [
            "22411",
            "22452"
        ],
        "desa": {
            "href": "https://kodepos.nomor.net/_kodepos.php?_i=desa-kodepos&sby=000000&daerah=Kecamatan-Kab.-Tapanuli%20Utara&jobs=Tarutung",
            "jumlah": "31"
        },
        "pulau": null,
        "kode": "12.02.01"
    }
]