[
    {
        "code": "7403262007",
        "name": "Bhone Kainsetala (Bone Kancitala)",
        "poscode": "93663"
    },
    {
        "code": "7403262008",
        "name": "Bone Lolibu",
        "poscode": "93663"
    },
    {
        "code": "7403262006",
        "name": "Bone Tondo",
        "poscode": "93663"
    },
    {
        "code": "7403262010",
        "name": "Matombura",
        "poscode": "93663"
    },
    {
        "code": "7403262009",
        "name": "Oelongko",
        "poscode": "93663"
    }
]