[
    {
        "code": "3206122004",
        "name": "Cikalong",
        "poscode": "46473"
    },
    {
        "code": "3206122005",
        "name": "Cipaingeun",
        "poscode": "46473"
    },
    {
        "code": "3206122009",
        "name": "Cukangjayaguna",
        "poscode": "46473"
    },
    {
        "code": "3206122002",
        "name": "Cukangkawung",
        "poscode": "46473"
    },
    {
        "code": "3206122006",
        "name": "Leuwidulang",
        "poscode": "46473"
    },
    {
        "code": "3206122007",
        "name": "Muncang",
        "poscode": "46473"
    },
    {
        "code": "3206122011",
        "name": "Pakalongan",
        "poscode": "46473"
    },
    {
        "code": "3206122001",
        "name": "Parumasan",
        "poscode": "46473"
    },
    {
        "code": "3206122010",
        "name": "Raksajaya",
        "poscode": "46473"
    },
    {
        "code": "3206122008",
        "name": "Sepatnunggal",
        "poscode": "46473"
    },
    {
        "code": "3206122003",
        "name": "Sodonghilir",
        "poscode": "46473"
    },
    {
        "code": "3206122012",
        "name": "Sukabakti",
        "poscode": "46473"
    }
]