[
    {
        "code": "3326132012",
        "name": "Ambokembang",
        "poscode": "51173"
    },
    {
        "code": "3326132016",
        "name": "Bugangan (Bungangan)",
        "poscode": "51173"
    },
    {
        "code": "3326132015",
        "name": "Karangdowo",
        "poscode": "51173"
    },
    {
        "code": "3326132001",
        "name": "Kedungpatangewu (Kedung Patangewu)",
        "poscode": "51173"
    },
    {
        "code": "3326131020",
        "name": "Kedungwuni Barat",
        "poscode": "51173"
    },
    {
        "code": "3326131019",
        "name": "Kedungwuni Timur",
        "poscode": "51173"
    },
    {
        "code": "3326132008",
        "name": "Kwayangan",
        "poscode": "51173"
    },
    {
        "code": "3326132004",
        "name": "Langkap",
        "poscode": "51173"
    },
    {
        "code": "3326132006",
        "name": "Pajomblangan",
        "poscode": "51173"
    },
    {
        "code": "3326132002",
        "name": "Pakisputih",
        "poscode": "51173"
    },
    {
        "code": "3326131013",
        "name": "Pekajangan",
        "poscode": "51173"
    },
    {
        "code": "3326132010",
        "name": "Podo",
        "poscode": "51173"
    },
    {
        "code": "3326132007",
        "name": "Proto",
        "poscode": "51173"
    },
    {
        "code": "3326132017",
        "name": "Rengas",
        "poscode": "51173"
    },
    {
        "code": "3326132003",
        "name": "Rowocacing",
        "poscode": "51173"
    },
    {
        "code": "3326132011",
        "name": "Salakbrojo",
        "poscode": "51173"
    },
    {
        "code": "3326132018",
        "name": "Tangkilkulon (Tangkil Kulon)",
        "poscode": "51173"
    },
    {
        "code": "3326132014",
        "name": "Tangkiltengah (Tangkil Tengah)",
        "poscode": "51173"
    },
    {
        "code": "3326132005",
        "name": "Tosaran",
        "poscode": "51173"
    }
]