[
    {
        "code": "5314082002",
        "name": "Daleholu",
        "poscode": "85972"
    },
    {
        "code": "5314082003",
        "name": "Dodaek",
        "poscode": "85972"
    },
    {
        "code": "5314082005",
        "name": "Inaoe",
        "poscode": "85972"
    },
    {
        "code": "5314082001",
        "name": "Lenguselu",
        "poscode": "85972"
    },
    {
        "code": "5314082006",
        "name": "Nggelodae",
        "poscode": "85972"
    },
    {
        "code": "5314082007",
        "name": "Pilasue",
        "poscode": "85972"
    },
    {
        "code": "5314082004",
        "name": "Tebole",
        "poscode": "85972"
    }
]