[
    {
        "code": "3507162014",
        "name": "Benjor",
        "poscode": "65156"
    },
    {
        "code": "3507162006",
        "name": "Bokor",
        "poscode": "65156"
    },
    {
        "code": "3507162013",
        "name": "Duwet",
        "poscode": "65156"
    },
    {
        "code": "3507162015",
        "name": "Duwet Kerajan (Duwet Krajan)",
        "poscode": "65156"
    },
    {
        "code": "3507162009",
        "name": "Jeru",
        "poscode": "65156"
    },
    {
        "code": "3507162003",
        "name": "Kambingan",
        "poscode": "65156"
    },
    {
        "code": "3507162002",
        "name": "Kidal",
        "poscode": "65156"
    },
    {
        "code": "3507162010",
        "name": "Malangsuko",
        "poscode": "65156"
    },
    {
        "code": "3507162001",
        "name": "Ngingit",
        "poscode": "65156"
    },
    {
        "code": "3507162004",
        "name": "Pandanajeng",
        "poscode": "65156"
    },
    {
        "code": "3507162005",
        "name": "Pulungdowo",
        "poscode": "65156"
    },
    {
        "code": "3507162007",
        "name": "Slamet",
        "poscode": "65156"
    },
    {
        "code": "3507162012",
        "name": "Tulusbesar",
        "poscode": "65156"
    },
    {
        "code": "3507162011",
        "name": "Tumpang",
        "poscode": "65156"
    },
    {
        "code": "3507162008",
        "name": "Wringinsongo",
        "poscode": "65156"
    }
]