[
    {
        "code": "7409082002",
        "name": "Bandaeha",
        "poscode": "93354"
    },
    {
        "code": "7409082015",
        "name": "Bendewuta",
        "poscode": "93354"
    },
    {
        "code": "7409082018",
        "name": "Horoe",
        "poscode": "93354"
    },
    {
        "code": "7409082003",
        "name": "Kota Maju",
        "poscode": "93354"
    },
    {
        "code": "7409082013",
        "name": "Lameoru",
        "poscode": "93354"
    },
    {
        "code": "7409082004",
        "name": "Landawe",
        "poscode": "93354"
    },
    {
        "code": "7409082001",
        "name": "Laronaha",
        "poscode": "93354"
    },
    {
        "code": "7409081009",
        "name": "Linomoiyo",
        "poscode": "93354"
    },
    {
        "code": "7409082006",
        "name": "Mopute",
        "poscode": "93354"
    },
    {
        "code": "7409082011",
        "name": "Paka Indah",
        "poscode": "93354"
    },
    {
        "code": "7409082008",
        "name": "Puuhialu",
        "poscode": "93354"
    },
    {
        "code": "7409082010",
        "name": "Sambandete",
        "poscode": "93354"
    },
    {
        "code": "7409082007",
        "name": "Tadoloiyo",
        "poscode": "93354"
    },
    {
        "code": "7409082019",
        "name": "Tadoloiyo Trans",
        "poscode": "93354"
    },
    {
        "code": "7409082016",
        "name": "Tinondo",
        "poscode": "93354"
    },
    {
        "code": "7409082014",
        "name": "Walandawe",
        "poscode": "93354"
    },
    {
        "code": "7409082005",
        "name": "Wiwirano",
        "poscode": "93354"
    }
]