[
    {
        "code": "3305152007",
        "name": "Adikarto",
        "poscode": "54363"
    },
    {
        "code": "3305152011",
        "name": "Adiluhur",
        "poscode": "54363"
    },
    {
        "code": "3305152008",
        "name": "Adimulyo",
        "poscode": "54363"
    },
    {
        "code": "3305152020",
        "name": "Arjomulyo",
        "poscode": "54363"
    },
    {
        "code": "3305152021",
        "name": "Arjosari",
        "poscode": "54363"
    },
    {
        "code": "3305152016",
        "name": "Banyuroto",
        "poscode": "54363"
    },
    {
        "code": "3305152019",
        "name": "Bonjok",
        "poscode": "54363"
    },
    {
        "code": "3305152006",
        "name": "Candiwulan (Candi Wulan)",
        "poscode": "54363"
    },
    {
        "code": "3305152018",
        "name": "Caruban",
        "poscode": "54363"
    },
    {
        "code": "3305152010",
        "name": "Joho",
        "poscode": "54363"
    },
    {
        "code": "3305152014",
        "name": "Kemujan",
        "poscode": "54363"
    },
    {
        "code": "3305152015",
        "name": "Mangunharjo",
        "poscode": "54363"
    },
    {
        "code": "3305152017",
        "name": "Meles",
        "poscode": "54363"
    },
    {
        "code": "3305152022",
        "name": "Pekuwon",
        "poscode": "54363"
    },
    {
        "code": "3305152013",
        "name": "Sekarteja",
        "poscode": "54363"
    },
    {
        "code": "3305152023",
        "name": "Sidomukti (Sidamukti)",
        "poscode": "54363"
    },
    {
        "code": "3305152004",
        "name": "Sidomulyo (Sidamulyo)",
        "poscode": "54363"
    },
    {
        "code": "3305152001",
        "name": "Sugihwaras",
        "poscode": "54363"
    },
    {
        "code": "3305152002",
        "name": "Tambaharjo (Tambakharjo)",
        "poscode": "54363"
    },
    {
        "code": "3305152012",
        "name": "Tegalsari",
        "poscode": "54363"
    },
    {
        "code": "3305152009",
        "name": "Temanggal",
        "poscode": "54363"
    },
    {
        "code": "3305152003",
        "name": "Tepakyang",
        "poscode": "54363"
    },
    {
        "code": "3305152005",
        "name": "Wajasari",
        "poscode": "54363"
    }
]