[
    {
        "code": "3305072015",
        "name": "Ambalkebrek",
        "poscode": "54392"
    },
    {
        "code": "3305072012",
        "name": "Ambalkliwonan",
        "poscode": "54392"
    },
    {
        "code": "3305072004",
        "name": "Ambalresmi",
        "poscode": "54392"
    },
    {
        "code": "3305072022",
        "name": "Ambarwinangun",
        "poscode": "54392"
    },
    {
        "code": "3305072017",
        "name": "Banjarsari",
        "poscode": "54392"
    },
    {
        "code": "3305072011",
        "name": "Benerkulon",
        "poscode": "54392"
    },
    {
        "code": "3305072010",
        "name": "Benerwetan",
        "poscode": "54392"
    },
    {
        "code": "3305072009",
        "name": "Blengorkulon",
        "poscode": "54392"
    },
    {
        "code": "3305072008",
        "name": "Blengorwetan",
        "poscode": "54392"
    },
    {
        "code": "3305072031",
        "name": "Dukuhrejosari (Dukuhrejasari)",
        "poscode": "54392"
    },
    {
        "code": "3305072001",
        "name": "Entak",
        "poscode": "54392"
    },
    {
        "code": "3305072016",
        "name": "Gondanglegi",
        "poscode": "54392"
    },
    {
        "code": "3305072006",
        "name": "Kaibon",
        "poscode": "54392"
    },
    {
        "code": "3305072005",
        "name": "Kaibonpetangkuran",
        "poscode": "54392"
    },
    {
        "code": "3305072032",
        "name": "Kembangsawit",
        "poscode": "54392"
    },
    {
        "code": "3305072003",
        "name": "Kenoyojayan (Kenayajayan)",
        "poscode": "54392"
    },
    {
        "code": "3305072028",
        "name": "Kradenan",
        "poscode": "54392"
    },
    {
        "code": "3305072018",
        "name": "Lajer",
        "poscode": "54392"
    },
    {
        "code": "3305072029",
        "name": "Pagedangan",
        "poscode": "54392"
    },
    {
        "code": "3305072013",
        "name": "Pasarsenen",
        "poscode": "54392"
    },
    {
        "code": "3305072023",
        "name": "Peneket",
        "poscode": "54392"
    },
    {
        "code": "3305072002",
        "name": "Plempukan Kembaran (Plempukankembaran)",
        "poscode": "54392"
    },
    {
        "code": "3305072027",
        "name": "Prasutan",
        "poscode": "54392"
    },
    {
        "code": "3305072014",
        "name": "Pucangan",
        "poscode": "54392"
    },
    {
        "code": "3305072020",
        "name": "Sidoluhur",
        "poscode": "54392"
    },
    {
        "code": "3305072026",
        "name": "Sidomukti",
        "poscode": "54392"
    },
    {
        "code": "3305072025",
        "name": "Sidomulyo",
        "poscode": "54392"
    },
    {
        "code": "3305072024",
        "name": "Sidorejo (Sidareja)",
        "poscode": "54392"
    },
    {
        "code": "3305072019",
        "name": "Singosari",
        "poscode": "54392"
    },
    {
        "code": "3305072021",
        "name": "Sinungrejo (Sinungreja)",
        "poscode": "54392"
    },
    {
        "code": "3305072007",
        "name": "Sumberjati",
        "poscode": "54392"
    },
    {
        "code": "3305072030",
        "name": "Surobayan",
        "poscode": "54392"
    }
]