[
    {
        "code": "6102082010",
        "name": "Jungkat",
        "poscode": "78352"
    },
    {
        "code": "6102082006",
        "name": "Peniti Luar",
        "poscode": "78352"
    },
    {
        "code": "6102082002",
        "name": "Sei/Sungai Nipah",
        "poscode": "78352"
    },
    {
        "code": "6102082001",
        "name": "Wajok Hilir (Wajo Hilir)",
        "poscode": "78352"
    },
    {
        "code": "6102082009",
        "name": "Wajok Hulu (Wajo Hulu)",
        "poscode": "78352"
    }
]