[
    {
        "code": "3203132005",
        "name": "Cibadak",
        "poscode": "43254"
    },
    {
        "code": "3203132008",
        "name": "Cibanteng",
        "poscode": "43254"
    },
    {
        "code": "3203132002",
        "name": "Cikancana",
        "poscode": "43254"
    },
    {
        "code": "3203132001",
        "name": "Cikanyere",
        "poscode": "43254"
    },
    {
        "code": "3203132003",
        "name": "Ciwalen",
        "poscode": "43254"
    },
    {
        "code": "3203132004",
        "name": "Kawungluwuk",
        "poscode": "43254"
    },
    {
        "code": "3203132009",
        "name": "Kubang",
        "poscode": "43254"
    },
    {
        "code": "3203132010",
        "name": "Pakuon",
        "poscode": "43254"
    },
    {
        "code": "3203132011",
        "name": "Rawabelut",
        "poscode": "43254"
    },
    {
        "code": "3203132006",
        "name": "Sukamahi",
        "poscode": "43254"
    },
    {
        "code": "3203132007",
        "name": "Sukaresmi",
        "poscode": "43254"
    }
]