[
    {
        "code": "130713",
        "name": "Akabiluru",
        "count": {
            "desa": 7
        }
    },
    {
        "code": "130712",
        "name": "Bukik Barisan",
        "count": {
            "desa": 5
        }
    },
    {
        "code": "130702",
        "name": "Guguak (Gugu)",
        "count": {
            "desa": 5
        }
    },
    {
        "code": "130708",
        "name": "Gunuang Omeh (Gunung Mas)",
        "count": {
            "desa": 3
        }
    },
    {
        "code": "130705",
        "name": "Harau",
        "count": {
            "desa": 11
        }
    },
    {
        "code": "130707",
        "name": "Kapur IX/Sembilan",
        "count": {
            "desa": 7
        }
    },
    {
        "code": "130709",
        "name": "Lareh Sago Halaban",
        "count": {
            "desa": 8
        }
    },
    {
        "code": "130704",
        "name": "Luak (Luhak)",
        "count": {
            "desa": 4
        }
    },
    {
        "code": "130711",
        "name": "Mungka",
        "count": {
            "desa": 5
        }
    },
    {
        "code": "130706",
        "name": "Pangkalan Koto Baru",
        "count": {
            "desa": 6
        }
    },
    {
        "code": "130703",
        "name": "Payakumbuh",
        "count": {
            "desa": 7
        }
    },
    {
        "code": "130710",
        "name": "Situjuah Limo/Lima Nagari",
        "count": {
            "desa": 5
        }
    },
    {
        "code": "130701",
        "name": "Suliki",
        "count": {
            "desa": 6
        }
    }
]