[
    {
        "code": "7501232002",
        "name": "Bilato",
        "poscode": "96234"
    },
    {
        "code": "7501232007",
        "name": "Bumela",
        "poscode": "96234"
    },
    {
        "code": "7501232003",
        "name": "Ilomata",
        "poscode": "96234"
    },
    {
        "code": "7501232005",
        "name": "Juriya",
        "poscode": "96234"
    },
    {
        "code": "7501232008",
        "name": "Lamahu",
        "poscode": "96234"
    },
    {
        "code": "7501232009",
        "name": "Musyawarah",
        "poscode": "96234"
    },
    {
        "code": "7501232006",
        "name": "Pelehu",
        "poscode": "96234"
    },
    {
        "code": "7501232010",
        "name": "Suka Damai",
        "poscode": "96234"
    },
    {
        "code": "7501232004",
        "name": "Taula'a (Taulaa)",
        "poscode": "96234"
    },
    {
        "code": "7501232001",
        "name": "Totopo",
        "poscode": "96234"
    }
]