[
    {
        "code": "7505092004",
        "name": "Dunu",
        "poscode": "96526"
    },
    {
        "code": "7505092005",
        "name": "Garapia",
        "poscode": "96526"
    },
    {
        "code": "7505092008",
        "name": "Mokonowu",
        "poscode": "96526"
    },
    {
        "code": "7505092001",
        "name": "Monano",
        "poscode": "96526"
    },
    {
        "code": "7505092003",
        "name": "Monas",
        "poscode": "96526"
    },
    {
        "code": "7505092007",
        "name": "Pilohulata",
        "poscode": "96526"
    },
    {
        "code": "7505092006",
        "name": "Sogu",
        "poscode": "96526"
    },
    {
        "code": "7505092009",
        "name": "Tolitehuyu",
        "poscode": "96526"
    },
    {
        "code": "7505092002",
        "name": "Tudi",
        "poscode": "96526"
    },
    {
        "code": "7505092010",
        "name": "Zuriyati",
        "poscode": "96526"
    }
]