[
    {
        "code": "9503362006",
        "name": "Bineleruk",
        "poscode": "99733"
    },
    {
        "code": "9503362002",
        "name": "Danggema",
        "poscode": "99733"
    },
    {
        "code": "9503362001",
        "name": "Holuwon (Holuon)",
        "poscode": "99733"
    },
    {
        "code": "9503362005",
        "name": "Sia",
        "poscode": "99733"
    },
    {
        "code": "9503362007",
        "name": "Sohonggik",
        "poscode": "99733"
    },
    {
        "code": "9503362004",
        "name": "Sosi",
        "poscode": "99733"
    },
    {
        "code": "9503362003",
        "name": "Weni",
        "poscode": "99733"
    }
]