[
    {
        "code": "3404022004",
        "name": "Sidoagung",
        "poscode": "55264"
    },
    {
        "code": "3404022006",
        "name": "Sidoarum",
        "poscode": "55264"
    },
    {
        "code": "3404022005",
        "name": "Sidokarto",
        "poscode": "55264"
    },
    {
        "code": "3404022002",
        "name": "Sidoluhur",
        "poscode": "55264"
    },
    {
        "code": "3404022007",
        "name": "Sidomoyo",
        "poscode": "55264"
    },
    {
        "code": "3404022003",
        "name": "Sidomulyo",
        "poscode": "55264"
    },
    {
        "code": "3404022001",
        "name": "Sidorejo",
        "poscode": "55264"
    }
]