[
    {
        "code": "3604292007",
        "name": "Barugbug",
        "poscode": "42168"
    },
    {
        "code": "3604292008",
        "name": "Batu Kuwung (Batukuwung)",
        "poscode": "42168"
    },
    {
        "code": "3604292002",
        "name": "Bugel",
        "poscode": "42168"
    },
    {
        "code": "3604292003",
        "name": "Cibojong",
        "poscode": "42168"
    },
    {
        "code": "3604292006",
        "name": "Ciomas",
        "poscode": "42168"
    },
    {
        "code": "3604292012",
        "name": "Cipayung",
        "poscode": "42168"
    },
    {
        "code": "3604292005",
        "name": "Cisaat",
        "poscode": "42168"
    },
    {
        "code": "3604292004",
        "name": "Citasuk",
        "poscode": "42168"
    },
    {
        "code": "3604292013",
        "name": "Curug Goong",
        "poscode": "42168"
    },
    {
        "code": "3604292014",
        "name": "Kadu Kempong",
        "poscode": "42168"
    },
    {
        "code": "3604292011",
        "name": "Kadubeureum",
        "poscode": "42168"
    },
    {
        "code": "3604292010",
        "name": "Kelumpang (Kalumpang)",
        "poscode": "42168"
    },
    {
        "code": "3604292009",
        "name": "Kramatlaban",
        "poscode": "42168"
    },
    {
        "code": "3604292001",
        "name": "Padarincang",
        "poscode": "42168"
    }
]