[
    {
        "code": "1406112003",
        "name": "Bona Tapung (Bono Tapung)",
        "poscode": "28552"
    },
    {
        "code": "1406112004",
        "name": "Dayo",
        "poscode": "28552"
    },
    {
        "code": "1406112008",
        "name": "Koto Tandun",
        "poscode": "28552"
    },
    {
        "code": "1406112002",
        "name": "Kumain",
        "poscode": "28552"
    },
    {
        "code": "1406112006",
        "name": "Puo Raya",
        "poscode": "28552"
    },
    {
        "code": "1406112007",
        "name": "Sei/Sungai Kuning",
        "poscode": "28552"
    },
    {
        "code": "1406112001",
        "name": "Tandun",
        "poscode": "28552"
    },
    {
        "code": "1406112009",
        "name": "Tandun Barat",
        "poscode": "28552"
    },
    {
        "code": "1406112005",
        "name": "Tapung Jaya",
        "poscode": "28552"
    }
]