[
    {
        "code": "3217052003",
        "name": "Bojongmekar",
        "poscode": "40558"
    },
    {
        "code": "3217052002",
        "name": "Ciharashas",
        "poscode": "40558"
    },
    {
        "code": "3217052001",
        "name": "Cipeundeuy",
        "poscode": "40558"
    },
    {
        "code": "3217052004",
        "name": "Ciroyom",
        "poscode": "40558"
    },
    {
        "code": "3217052005",
        "name": "Jatimekar",
        "poscode": "40558"
    },
    {
        "code": "3217052006",
        "name": "Margalaksana",
        "poscode": "40558"
    },
    {
        "code": "3217052007",
        "name": "Margaluyu",
        "poscode": "40558"
    },
    {
        "code": "3217052008",
        "name": "Nanggeleng",
        "poscode": "40558"
    },
    {
        "code": "3217052009",
        "name": "Nyenang",
        "poscode": "40558"
    },
    {
        "code": "3217052011",
        "name": "Sirnagalih",
        "poscode": "40558"
    },
    {
        "code": "3217052010",
        "name": "Sirnaraja",
        "poscode": "40558"
    },
    {
        "code": "3217052012",
        "name": "Sukahaji",
        "poscode": "40558"
    }
]