[
    {
        "code": "9207082003",
        "name": "Isey (Isei)",
        "poscode": "98343"
    },
    {
        "code": "9207082008",
        "name": "Nggatum",
        "poscode": "98343"
    },
    {
        "code": "9207082001",
        "name": "Rasiey (Rasiei)",
        "poscode": "98343"
    },
    {
        "code": "9207082005",
        "name": "Sasirey (Sasirei)",
        "poscode": "98343"
    },
    {
        "code": "9207082009",
        "name": "Senderawoy / Senderawoi (Sindrawoi)",
        "poscode": "98343"
    },
    {
        "code": "9207082006",
        "name": "Tandia",
        "poscode": "98343"
    },
    {
        "code": "9207082002",
        "name": "Torey",
        "poscode": "98343"
    },
    {
        "code": "9207082004",
        "name": "Uryemi (Uriyem/Uriemi)",
        "poscode": "98343"
    },
    {
        "code": "9207082007",
        "name": "Webi",
        "poscode": "98343"
    }
]