[
    {
        "code": "1813032007",
        "name": "Bambang",
        "poscode": "34877"
    },
    {
        "code": "1813032009",
        "name": "Bandar Pugung",
        "poscode": "34877"
    },
    {
        "code": "1813032005",
        "name": "Cahaya Negeri",
        "poscode": "34877"
    },
    {
        "code": "1813032004",
        "name": "Lemong",
        "poscode": "34877"
    },
    {
        "code": "1813032006",
        "name": "Malaya",
        "poscode": "34877"
    },
    {
        "code": "1813032008",
        "name": "Pagar Dalam",
        "poscode": "34877"
    },
    {
        "code": "1813032013",
        "name": "Parda Haga",
        "poscode": "34883"
    },
    {
        "code": "1813032010",
        "name": "Penengahan (Pengehan)",
        "poscode": "34877"
    },
    {
        "code": "1813032011",
        "name": "Rata Agung",
        "poscode": "34877"
    },
    {
        "code": "1813032012",
        "name": "Sukamulya (Suka Mulya)",
        "poscode": "34883"
    },
    {
        "code": "1813032001",
        "name": "Tanjung Jati",
        "poscode": "34877"
    },
    {
        "code": "1813032002",
        "name": "Tanjung Sakti",
        "poscode": "34877"
    },
    {
        "code": "1813032003",
        "name": "Way Batang",
        "poscode": "34877"
    }
]