[
    {
        "code": "1607072008",
        "name": "Air Gading",
        "poscode": "30975"
    },
    {
        "code": "1607072011",
        "name": "Daya Makmur",
        "poscode": "30975"
    },
    {
        "code": "1607072010",
        "name": "Daya Utama",
        "poscode": "30975"
    },
    {
        "code": "1607072003",
        "name": "Karang Anyar",
        "poscode": "30975"
    },
    {
        "code": "1607072037",
        "name": "Margo Mulyo 20 (Margomulyo 20)",
        "poscode": "30975"
    },
    {
        "code": "1607072038",
        "name": "Margo Sugihan (Marga Sugihan)",
        "poscode": "30975"
    },
    {
        "code": "1607072001",
        "name": "Muara Padang",
        "poscode": "30975"
    },
    {
        "code": "1607072006",
        "name": "Purwodadi",
        "poscode": "30975"
    },
    {
        "code": "1607072012",
        "name": "Sido Mulyo 18 (Sidomulyo 18)",
        "poscode": "30975"
    },
    {
        "code": "1607072018",
        "name": "Sido Mulyo 20 (Sidomulyo 20)",
        "poscode": "30975"
    },
    {
        "code": "1607072013",
        "name": "Sido Rejo (Sidorejo)",
        "poscode": "30975"
    },
    {
        "code": "1607072007",
        "name": "Sumber Makmur",
        "poscode": "30975"
    },
    {
        "code": "1607072002",
        "name": "Tanjungbaru (Tanjung Baru)",
        "poscode": "30975"
    },
    {
        "code": "1607072042",
        "name": "Tirta Jaya",
        "poscode": "30975"
    },
    {
        "code": "1607072009",
        "name": "Tirto Raharjo",
        "poscode": "30975"
    }
]